biobridge/__about__.py
biobridge/blocks/cell.py
biobridge/blocks/protein.py
biobridge/blocks/tissue.py
biobridge/definitions/chromosome_pair.py
biobridge/definitions/enzyme.py
biobridge/definitions/hormone.py
biobridge/definitions/organ.py
biobridge/definitions/organism.py
biobridge/definitions/virus.py
biobridge/definitions/cells/epithelial_cell.py
biobridge/definitions/cells/eukaryotic_cell.py
biobridge/definitions/cells/germ_cell.py
biobridge/definitions/cells/muscle_cell.py
biobridge/definitions/cells/neuron_cell.py
biobridge/definitions/cells/organ.py
biobridge/definitions/cells/plant.py
biobridge/definitions/cells/platelet.py
biobridge/definitions/cells/red_blood_cell.py
biobridge/definitions/cells/somatic_cell.py
biobridge/definitions/cells/stem_cell.py
biobridge/definitions/infections/hsv.py
biobridge/definitions/organisms/ao.py
biobridge/definitions/organisms/bacteria.py
biobridge/definitions/organisms/mycelium.py
biobridge/definitions/organisms/plant.py
biobridge/definitions/proteins/collagen.py
biobridge/definitions/proteins/enzyme.py
biobridge/definitions/proteins/hemoglobin.py
biobridge/definitions/proteins/histones.py
biobridge/definitions/proteins/keratin.py
biobridge/definitions/proteins/signaling.py
biobridge/definitions/proteins/structural.py
biobridge/definitions/proteins/transport.py
biobridge/definitions/tissues/bone.py
biobridge/definitions/tissues/breast.py
biobridge/definitions/tissues/epithelial.py
biobridge/definitions/tissues/fat.py
biobridge/definitions/tissues/muscle.py
biobridge/definitions/tissues/neural.py
biobridge/definitions/tissues/organ.py
biobridge/definitions/tissues/radiation_affected.py
biobridge/definitions/tissues/vascular.py
biobridge/dnalite/deploy.py
biobridge/dnalite/sqld.py
biobridge/enviromental/environment.py
biobridge/enviromental/infection.py
biobridge/enviromental/visualize.py
biobridge/enviromental/visualizer.py
biobridge/genes/chromosome.py
biobridge/genes/dna.py
biobridge/genes/gene.py
biobridge/genes/mRNA.py
biobridge-0.2.7.dist-info/METADATA
biobridge-0.2.7.dist-info/WHEEL
biobridge-0.2.7.dist-info/RECORD
