Metadata-Version: 2.4
Name: biobridge
Version: 0.2.7
Summary: A library for simulating all biology related things, analyzing them and visualizing them.
Project-URL: Documentation, https://github.com/Okerew/biobridge#readme
Project-URL: Issues, https://github.com/Okerew/biobridge/issues
Project-URL: Source, https://github.com/Okerew/biobridge
Author-email: Okerew <okerewgroup@proton.me>
License-Expression: MIT
Requires-Python: >=3.8
Requires-Dist: biopython~=1.84
Requires-Dist: flask~=3.0.3
Requires-Dist: imageio~=2.35.1
Requires-Dist: matplotlib~=3.9.2
Requires-Dist: mediapipe~=0.10.15
Requires-Dist: networkx~=3.3
Requires-Dist: numpy~=1.26.4
Requires-Dist: opencv-python~=4.10.0.84
Requires-Dist: pandas~=2.2.2
Requires-Dist: pillow~=10.4.0
Requires-Dist: py3dmol~=2.3.0
Requires-Dist: pytesseract~=0.3.13
Requires-Dist: requests~=2.32.3
Requires-Dist: scikit-image~=0.24.0
Requires-Dist: scikit-learn~=1.5.1
Requires-Dist: scipy~=1.14.1
Requires-Dist: torch~=2.8.0
